gdmec23120145/__init__.py
gdmec23120145-0.1.0.dist-info/METADATA
gdmec23120145-0.1.0.dist-info/WHEEL
gdmec23120145-0.1.0.dist-info/entry_points.txt
gdmec23120145-0.1.0.dist-info/RECORD
